box_kernel/__init__.py
box_kernel/__main__.py
box_kernel/install.py
box_kernel/kernel.py
box_kernel_stauffenbits-1.6.dist-info/LICENSE
box_kernel_stauffenbits-1.6.dist-info/METADATA
box_kernel_stauffenbits-1.6.dist-info/WHEEL
box_kernel_stauffenbits-1.6.dist-info/top_level.txt
box_kernel_stauffenbits-1.6.dist-info/RECORD
