Metadata-Version: 2.1
Name: box-kernel-stauffenbits
Version: 1.6
Summary: Simple box kernel for Jupyter
Home-page: https://github.com/stauffenbits/box_kernel
Author: Joshua M. Moore
Author-email: moore.joshua@pm.me
License: UNKNOWN
Platform: UNKNOWN
Classifier: Intended Audience :: Developers
Classifier: License :: OSI Approved :: BSD License
Classifier: Programming Language :: Python :: 3
